praudio/__init__.py
praudio/errors.py
praudio/preprocess.py
praudio/transformschain.py
praudio/utils.py
praudio/version.py
praudio/config/__init__.py
praudio/config/configloader.py
praudio/config/configsaver.py
praudio/config/configvalidator.py
praudio/creation/__init__.py
praudio/creation/batchfilepreprocessorcreator.py
praudio/creation/filepreprocessorcreator.py
praudio/creation/transformfactory.py
praudio/creation/transformschaincreator.py
praudio/io/__init__.py
praudio/io/loader.py
praudio/io/numpysaver.py
praudio/io/saver.py
praudio/io/signal.py
praudio/preprocessors/__init__.py
praudio/preprocessors/batchfilepreprocessor.py
praudio/preprocessors/filepreprocessor.py
praudio/transforms/__init__.py
praudio/transforms/log.py
praudio/transforms/magnitudespectrogram.py
praudio/transforms/melspectrogram.py
praudio/transforms/mfcc.py
praudio/transforms/powerspectrogram.py
praudio/transforms/stft.py
praudio/transforms/transform.py
praudio/transforms/scaling/__init__.py
praudio/transforms/scaling/minmaxscaler.py
praudio/transforms/scaling/rowstandardiser.py
praudio/transforms/scaling/scaler.py
praudio/transforms/scaling/standardiser.py
praudio-0.1.0.dist-info/LICENSE
praudio-0.1.0.dist-info/METADATA
praudio-0.1.0.dist-info/WHEEL
praudio-0.1.0.dist-info/entry_points.txt
praudio-0.1.0.dist-info/top_level.txt
praudio-0.1.0.dist-info/RECORD
