Metadata-Version: 2.1
Name: praudio
Version: 0.1.0
Summary: Complex preprocessing of entire audio datasets with 1 command
Home-page: https://github.com/musikalkemist/praudio
Author: Valerio Velardo
Author-email: velardovalerio@gmail.com
License: UNKNOWN
Project-URL: Source, https://github.com/musikalkemist/praudio
Project-URL: Tracker, https://github.com/musikalkemist/praudio/issues
Platform: UNKNOWN
Classifier: Programming Language :: Python :: 3
Classifier: Programming Language :: Python :: 3.7
Classifier: Programming Language :: Python :: 3.8
Classifier: Programming Language :: Python :: 3.9
Requires-Python: >=3.7
Requires-Dist: numpy (==1.20.3)
Requires-Dist: librosa (==0.8.1)
Requires-Dist: pyyaml (==5.4.1)
Requires-Dist: types-PyYAML (==5.4.6)
Provides-Extra: testing
Requires-Dist: pytest ; extra == 'testing'
Requires-Dist: coverage ; extra == 'testing'
Requires-Dist: pytest-mock ; extra == 'testing'
Requires-Dist: pylint ; extra == 'testing'
Requires-Dist: mypy ; extra == 'testing'
